config_reading/__init__.py
config_reading/json.py
config_reading/python.py
config_reading/read.py
config_reading/toml.py
config_reading/yaml.py
config_reading-0.1.4.dist-info/licenses/LICENSE
config_reading-0.1.4.dist-info/METADATA
config_reading-0.1.4.dist-info/WHEEL
config_reading-0.1.4.dist-info/entry_points.txt
config_reading-0.1.4.dist-info/top_level.txt
config_reading-0.1.4.dist-info/RECORD
