Metadata-Version: 2.4
Name: config-reading
Version: 0.1.4
Summary: Configuration reading extensibility point for your package via python entry-points mechanism.
Author-email: Vitalii Stepanenko <mail@vitaliy.in>
Maintainer-email: Vitalii Stepanenko <mail@vitaliy.in>
License: MIT License
Project-URL: Source Code, https://github.com/Nayjest/config_reading
Requires-Python: >=3.12
License-File: LICENSE
Provides-Extra: yaml
Requires-Dist: pyyaml; extra == "yaml"
Dynamic: license-file
